[
    {
        "headline": "policja",
        "first_cell": "94",
        "second_cell": "115",
        "other_words": "policjanta,policjanci,policjantów,policja"
    },
    {
        "headline": "ukrainy",
        "first_cell": "161",
        "second_cell": "275",
        "other_words": "ukrainy,ukraińców,ukraińskie"
    },
    {
        "headline": "rosjan",
        "first_cell": "212",
        "second_cell": "313",
        "other_words": "rosyjski,rosyjscy,rosyjskich,rosjanie"
    },
    {
        "headline": "pis",
        "first_cell": "78",
        "second_cell": "72",
        "other_words": "None"
    },
    {
        "headline": "tuska",
        "first_cell": "2",
        "second_cell": "145",
        "other_words": "tusk,tuska"
    }
]